xtsv/__init__.py
xtsv/argparser.py
xtsv/jnius_wrapper.py
xtsv/pipeline.py
xtsv/tsvhandler.py
xtsv/version.py
xtsv/templates/layout.html
xtsv-1.4.2.dist-info/LICENSE
xtsv-1.4.2.dist-info/METADATA
xtsv-1.4.2.dist-info/WHEEL
xtsv-1.4.2.dist-info/top_level.txt
xtsv-1.4.2.dist-info/RECORD
