Metadata-Version: 2.1
Name: xtsv
Version: 1.4.2
Summary: A generic TSV-style format based intermodular communication framework and REST API
Home-page: https://github.com/nytud/xtsv
Author: dlazesz
Author-email: devel@oliphant.nytud.hu
License: UNKNOWN
Platform: UNKNOWN
Classifier: Programming Language :: Python :: 3
Classifier: License :: OSI Approved :: GNU Lesser General Public License v3 (LGPLv3)
Classifier: Operating System :: OS Independent
Requires-Python: >=3.7
License-File: LICENSE
Requires-Dist: flask
Requires-Dist: flask-restful
Requires-Dist: werkzeug
